{
  "$schema": "https://raw.githubusercontent.com/dineug/erd-editor/main/json-schema/schema.json",
  "version": "3.0.0",
  "settings": {
    "width": 2000,
    "height": 2000,
    "scrollTop": -257.3385,
    "scrollLeft": -193.71,
    "zoomLevel": 0.73,
    "show": 431,
    "database": 4,
    "databaseName": "",
    "canvasType": "ERD",
    "language": 1,
    "tableNameCase": 4,
    "columnNameCase": 2,
    "bracketType": 1,
    "relationshipDataTypeSync": true,
    "relationshipOptimization": false,
    "columnOrder": [
      1,
      2,
      4,
      8,
      16,
      32,
      64
    ],
    "maxWidthComment": -1,
    "ignoreSaveSettings": 0
  },
  "doc": {
    "tableIds": [
      "8CR3LUh7Bu6E2K05mcn_1",
      "9LsWnXQ9aNAfzXo7eTbcx",
      "ine2bTIkvQcuM8JenCMxe",
      "UECpcafYs5jqD4Jo9NzYu",
      "32DQc-8Kt8b4ICwfTxYbx",
      "L35OiQd2nzeUB99PqCeDp",
      "JgOK8KJIWMkp047nzUywE",
      "x7s47iTk7VF24-TR7pl-1",
      "Q9zTRpze3Ct-XInVhqy2O",
      "Zy6H_d4fEmMmQ6c1w9ngv",
      "QianxabkC7plIXeknbQ24",
      "JNxQVbXcTdRCSPeXcfoII",
      "YtVYbPYV1bAvrPaLvH0Vr",
      "5dHesMonnOs6bORmG-b_M"
    ],
    "relationshipIds": [
      "m0Az5BGIEZoUg45vhnAJC",
      "YsMnr6maLTkx3jvDCpCCL",
      "D5oWdKVx7ak4WFyKNfLB_",
      "8uwB5RWuMGtoeEtpHmbtT",
      "AWMGbkcnmF_XmtedoHUfM",
      "uWiHvYVIhZXExPL7_wz6L",
      "FZ1_VBBbh8kT4Yg8kCVVd",
      "7_zab4jHHCB_G3M7h7s_n",
      "Jazl1WYFgzFc92m5Woi53",
      "Fgvp8Ln0o3RL5Oa7yrd8x",
      "xJgE60TVswrGbI4OJcFA8",
      "C0xf5tBJob8rp-ZuqWMa4",
      "XsI0of2u7hNW6SsRTSYdn",
      "MJE-sSUl4563d0zeG8nTi",
      "DLXefKcCVqoJxpxTMqjZ5",
      "mNP-5qpgEVbwRPn8R1NMs",
      "b5ru3fwcXNfo30Wvse_12"
    ],
    "indexIds": [],
    "memoIds": []
  },
  "collections": {
    "tableEntities": {
      "8CR3LUh7Bu6E2K05mcn_1": {
        "id": "8CR3LUh7Bu6E2K05mcn_1",
        "name": "Propiedad",
        "comment": "",
        "columnIds": [
          "a5elWrybvmcG4iFuMdC3_",
          "WJ4DpwMrTNJYMVuExLcku",
          "_ITbmM5CoNf9gKXkEjIEb",
          "y4KvWtTYP5JkQyTl04qSw",
          "5tul_fHFqnHCw3_UGWzli",
          "vGHJTPArO0DhAbOZ0Kt-e",
          "s56b71V8S6iJwFJ9vUDcB"
        ],
        "seqColumnIds": [
          "a5elWrybvmcG4iFuMdC3_",
          "WJ4DpwMrTNJYMVuExLcku",
          "_ITbmM5CoNf9gKXkEjIEb",
          "dVyyRAQs6Q0a4FAlAL2NV",
          "y4KvWtTYP5JkQyTl04qSw",
          "5tul_fHFqnHCw3_UGWzli",
          "vGHJTPArO0DhAbOZ0Kt-e",
          "s56b71V8S6iJwFJ9vUDcB"
        ],
        "ui": {
          "x": 738.6185,
          "y": 297.0925,
          "zIndex": 2,
          "widthName": 60,
          "widthComment": 60,
          "color": ""
        },
        "meta": {
          "updateAt": 1747777127018,
          "createAt": 1747774781958
        }
      },
      "9LsWnXQ9aNAfzXo7eTbcx": {
        "id": "9LsWnXQ9aNAfzXo7eTbcx",
        "name": "Usuario",
        "comment": "",
        "columnIds": [
          "9JgLy7mw9-__CTecA4awu",
          "628tXiY8Gy0Pch8Zdgi_O",
          "zu1IWPs5vTy84TVlxcTxi",
          "PP2F4Jel-PojUbzOTFvVv"
        ],
        "seqColumnIds": [
          "9JgLy7mw9-__CTecA4awu",
          "628tXiY8Gy0Pch8Zdgi_O",
          "zu1IWPs5vTy84TVlxcTxi",
          "PP2F4Jel-PojUbzOTFvVv"
        ],
        "ui": {
          "x": 1581.584,
          "y": 303.2553,
          "zIndex": 36,
          "widthName": 60,
          "widthComment": 60,
          "color": ""
        },
        "meta": {
          "updateAt": 1747777091777,
          "createAt": 1747775340407
        }
      },
      "ine2bTIkvQcuM8JenCMxe": {
        "id": "ine2bTIkvQcuM8JenCMxe",
        "name": "AgenteInmo",
        "comment": "",
        "columnIds": [
          "M7f5Y8k7tINzo7vqPXCu3",
          "Nfi4QI4AwNQ7y9YgIszbv",
          "HfusV_diGDY1MxIpoYQSm",
          "BPb6M5f0eyH3Wyu6rSV-a"
        ],
        "seqColumnIds": [
          "M7f5Y8k7tINzo7vqPXCu3",
          "Nfi4QI4AwNQ7y9YgIszbv",
          "HfusV_diGDY1MxIpoYQSm",
          "BPb6M5f0eyH3Wyu6rSV-a"
        ],
        "ui": {
          "x": 1301.8858,
          "y": 915.797,
          "zIndex": 65,
          "widthName": 68,
          "widthComment": 60,
          "color": ""
        },
        "meta": {
          "updateAt": 1747777095619,
          "createAt": 1747775453783
        }
      },
      "UECpcafYs5jqD4Jo9NzYu": {
        "id": "UECpcafYs5jqD4Jo9NzYu",
        "name": "VisitaPro",
        "comment": "",
        "columnIds": [
          "czo1ePlKeE86yqB8Tzy71",
          "2bD53c6vrEt1dwBku7WAZ",
          "5MghgRmLD_5JS5nHmvv1i",
          "GAHtiB3XTmiALQLEjwvos",
          "El8rdhaQJQ4UdBo3jz64n"
        ],
        "seqColumnIds": [
          "czo1ePlKeE86yqB8Tzy71",
          "2bD53c6vrEt1dwBku7WAZ",
          "5MghgRmLD_5JS5nHmvv1i",
          "GAHtiB3XTmiALQLEjwvos",
          "El8rdhaQJQ4UdBo3jz64n"
        ],
        "ui": {
          "x": 1409.1667,
          "y": 37.2822,
          "zIndex": 88,
          "widthName": 60,
          "widthComment": 60,
          "color": ""
        },
        "meta": {
          "updateAt": 1747777089229,
          "createAt": 1747775615671
        }
      },
      "32DQc-8Kt8b4ICwfTxYbx": {
        "id": "32DQc-8Kt8b4ICwfTxYbx",
        "name": "Publicacion",
        "comment": "",
        "columnIds": [
          "KkvXjknKbX7B5X-cumGZe",
          "KN-dxpfvX73zgXOZWE6V9",
          "N1UeOGXk8l6qj4TPTJcUc",
          "JWNYoVwL--kCG0n-9ef69",
          "VCO6qcs9jiBSCD7YtOWFx"
        ],
        "seqColumnIds": [
          "KkvXjknKbX7B5X-cumGZe",
          "KN-dxpfvX73zgXOZWE6V9",
          "N1UeOGXk8l6qj4TPTJcUc",
          "JWNYoVwL--kCG0n-9ef69",
          "Jrho93-J0SnjsFwhkIzU6",
          "VCO6qcs9jiBSCD7YtOWFx"
        ],
        "ui": {
          "x": 742.6705,
          "y": 29.0654,
          "zIndex": 93,
          "widthName": 62,
          "widthComment": 60,
          "color": ""
        },
        "meta": {
          "updateAt": 1747777108641,
          "createAt": 1747775651668
        }
      },
      "L35OiQd2nzeUB99PqCeDp": {
        "id": "L35OiQd2nzeUB99PqCeDp",
        "name": "Reseña",
        "comment": "",
        "columnIds": [
          "NsmDn9TD7cfFwHLIe16JI",
          "XoJjeY9qQQKZ0syZfm1wU",
          "8q_OzybaLdy6_kLSnC8o1",
          "28KfmFCUUOnQreRSS5q13",
          "ogWk7gsXrqxZlt13_hiUW",
          "5AFDkGa4rrE2vXhHsyFp9"
        ],
        "seqColumnIds": [
          "NsmDn9TD7cfFwHLIe16JI",
          "XoJjeY9qQQKZ0syZfm1wU",
          "8q_OzybaLdy6_kLSnC8o1",
          "28KfmFCUUOnQreRSS5q13",
          "ogWk7gsXrqxZlt13_hiUW",
          "5AFDkGa4rrE2vXhHsyFp9"
        ],
        "ui": {
          "x": 1573.798,
          "y": 615.0032,
          "zIndex": 98,
          "widthName": 60,
          "widthComment": 60,
          "color": ""
        },
        "meta": {
          "updateAt": 1747776676028,
          "createAt": 1747775732724
        }
      },
      "JgOK8KJIWMkp047nzUywE": {
        "id": "JgOK8KJIWMkp047nzUywE",
        "name": "TipoPro",
        "comment": "",
        "columnIds": [
          "id2kmU8xcDxJf0mA_2GvE"
        ],
        "seqColumnIds": [
          "id2kmU8xcDxJf0mA_2GvE",
          "It5YSy18HWegbYOBEmL1z"
        ],
        "ui": {
          "x": 245.8725,
          "y": 21.8244,
          "zIndex": 110,
          "widthName": 60,
          "widthComment": 60,
          "color": ""
        },
        "meta": {
          "updateAt": 1747776255496,
          "createAt": 1747775828057
        }
      },
      "x7s47iTk7VF24-TR7pl-1": {
        "id": "x7s47iTk7VF24-TR7pl-1",
        "name": "Departamento",
        "comment": "",
        "columnIds": [
          "iUiWEBF83HQ6QUBJlB3B5",
          "r0iv5VwOH2UhFZf8HOCsa"
        ],
        "seqColumnIds": [
          "iUiWEBF83HQ6QUBJlB3B5",
          "ykRa7iy7oS7-M-jXUo-kG",
          "r0iv5VwOH2UhFZf8HOCsa"
        ],
        "ui": {
          "x": 36.2057,
          "y": 717.2167,
          "zIndex": 116,
          "widthName": 79,
          "widthComment": 60,
          "color": ""
        },
        "meta": {
          "updateAt": 1747776714151,
          "createAt": 1747775869328
        }
      },
      "Q9zTRpze3Ct-XInVhqy2O": {
        "id": "Q9zTRpze3Ct-XInVhqy2O",
        "name": "Provincia",
        "comment": "",
        "columnIds": [
          "YGP1EAkKeux6T-uwjyV3U",
          "6VuQk97r0e_DpJLECfxtK",
          "IM9P-Ll101qZkiYwAPbwe"
        ],
        "seqColumnIds": [
          "YGP1EAkKeux6T-uwjyV3U",
          "6VuQk97r0e_DpJLECfxtK",
          "IM9P-Ll101qZkiYwAPbwe"
        ],
        "ui": {
          "x": 36.0032,
          "y": 494.3963,
          "zIndex": 121,
          "widthName": 60,
          "widthComment": 60,
          "color": ""
        },
        "meta": {
          "updateAt": 1747776712498,
          "createAt": 1747775898031
        }
      },
      "Zy6H_d4fEmMmQ6c1w9ngv": {
        "id": "Zy6H_d4fEmMmQ6c1w9ngv",
        "name": "Distrito",
        "comment": "",
        "columnIds": [
          "WmXGnVwLfffiRCMVKZPXj",
          "ijGqev_55c-Slqc2VgOU5",
          "ylmsizYo2iEEPl9KC35Rt"
        ],
        "seqColumnIds": [
          "WmXGnVwLfffiRCMVKZPXj",
          "ijGqev_55c-Slqc2VgOU5",
          "ylmsizYo2iEEPl9KC35Rt"
        ],
        "ui": {
          "x": 36.0345,
          "y": 280.028,
          "zIndex": 125,
          "widthName": 60,
          "widthComment": 60,
          "color": ""
        },
        "meta": {
          "updateAt": 1747776274181,
          "createAt": 1747775912626
        }
      },
      "QianxabkC7plIXeknbQ24": {
        "id": "QianxabkC7plIXeknbQ24",
        "name": "Dueño",
        "comment": "",
        "columnIds": [
          "j9PckDovgAyDVEmSAakl2",
          "vJUaprAztIhsfzTsE9btg",
          "IFXdeVPBeTeSpO0tPY0DE"
        ],
        "seqColumnIds": [
          "j9PckDovgAyDVEmSAakl2",
          "vJUaprAztIhsfzTsE9btg",
          "IFXdeVPBeTeSpO0tPY0DE"
        ],
        "ui": {
          "x": 23.1627,
          "y": 112.9046,
          "zIndex": 146,
          "widthName": 60,
          "widthComment": 60,
          "color": ""
        },
        "meta": {
          "updateAt": 1747776258603,
          "createAt": 1747776038113
        }
      },
      "JNxQVbXcTdRCSPeXcfoII": {
        "id": "JNxQVbXcTdRCSPeXcfoII",
        "name": "Contrato",
        "comment": "",
        "columnIds": [
          "0B-3n9R4F2AA5RHBGFngv",
          "bviFpjIfyRJ19NX6FteTd",
          "7nlM6yAoojrzXVtiI-G9s",
          "LKHGJl0iWdmcoRnrEV8_5",
          "h-wTro9ZagsloOzMvZAZX",
          "jxQXJJFp-W5WJj99fyImZ",
          "RdkkDnmVr8n8N8hQf2cZr"
        ],
        "seqColumnIds": [
          "0B-3n9R4F2AA5RHBGFngv",
          "bviFpjIfyRJ19NX6FteTd",
          "o0SFDeJHKdVro0EII5SNG",
          "7nlM6yAoojrzXVtiI-G9s",
          "LKHGJl0iWdmcoRnrEV8_5",
          "h-wTro9ZagsloOzMvZAZX",
          "jxQXJJFp-W5WJj99fyImZ",
          "RdkkDnmVr8n8N8hQf2cZr"
        ],
        "ui": {
          "x": 769.5317,
          "y": 631.6917,
          "zIndex": 157,
          "widthName": 60,
          "widthComment": 60,
          "color": ""
        },
        "meta": {
          "updateAt": 1747777123287,
          "createAt": 1747776105699
        }
      },
      "YtVYbPYV1bAvrPaLvH0Vr": {
        "id": "YtVYbPYV1bAvrPaLvH0Vr",
        "name": "TipoCont",
        "comment": "",
        "columnIds": [
          "ngEuDxk8kKKj1NfZ_gwt3",
          "oQ25oBTmxPwoNt9C-Rvs2"
        ],
        "seqColumnIds": [
          "ngEuDxk8kKKj1NfZ_gwt3",
          "oQ25oBTmxPwoNt9C-Rvs2"
        ],
        "ui": {
          "x": 765.0506,
          "y": 966.1248,
          "zIndex": 277,
          "widthName": 60,
          "widthComment": 60,
          "color": ""
        },
        "meta": {
          "updateAt": 1747777121797,
          "createAt": 1747776473923
        }
      },
      "5dHesMonnOs6bORmG-b_M": {
        "id": "5dHesMonnOs6bORmG-b_M",
        "name": "Pagos",
        "comment": "",
        "columnIds": [
          "vdJJcyNVV6gHN4o2dcmKj",
          "ayxZ1XrhAbvKEK2Hs1NTJ",
          "2_XtzvJfTMEVkpdA1ZHeG",
          "3yiBDSu0Fs8ZJjyQMLwzJ"
        ],
        "seqColumnIds": [
          "vdJJcyNVV6gHN4o2dcmKj",
          "ayxZ1XrhAbvKEK2Hs1NTJ",
          "2_XtzvJfTMEVkpdA1ZHeG",
          "3yiBDSu0Fs8ZJjyQMLwzJ"
        ],
        "ui": {
          "x": 238.4088,
          "y": 851.7051,
          "zIndex": 313,
          "widthName": 60,
          "widthComment": 60,
          "color": ""
        },
        "meta": {
          "updateAt": 1747777100532,
          "createAt": 1747776720981
        }
      }
    },
    "tableColumnEntities": {
      "a5elWrybvmcG4iFuMdC3_": {
        "id": "a5elWrybvmcG4iFuMdC3_",
        "tableId": "8CR3LUh7Bu6E2K05mcn_1",
        "name": "Pro_ID",
        "comment": "",
        "dataType": "INT",
        "default": "",
        "options": 10,
        "ui": {
          "keys": 1,
          "widthName": 60,
          "widthComment": 60,
          "widthDataType": 60,
          "widthDefault": 60
        },
        "meta": {
          "updateAt": 1747775216274,
          "createAt": 1747774809798
        }
      },
      "WJ4DpwMrTNJYMVuExLcku": {
        "id": "WJ4DpwMrTNJYMVuExLcku",
        "tableId": "8CR3LUh7Bu6E2K05mcn_1",
        "name": "Pro_Direccion",
        "comment": "",
        "dataType": "VARCHAR(100)",
        "default": "",
        "options": 0,
        "ui": {
          "keys": 0,
          "widthName": 74,
          "widthComment": 60,
          "widthDataType": 81,
          "widthDefault": 60
        },
        "meta": {
          "updateAt": 1747775279015,
          "createAt": 1747774937862
        }
      },
      "_ITbmM5CoNf9gKXkEjIEb": {
        "id": "_ITbmM5CoNf9gKXkEjIEb",
        "tableId": "8CR3LUh7Bu6E2K05mcn_1",
        "name": "Pro_Precio",
        "comment": "",
        "dataType": "MONEY",
        "default": "",
        "options": 0,
        "ui": {
          "keys": 0,
          "widthName": 60,
          "widthComment": 60,
          "widthDataType": 60,
          "widthDefault": 60
        },
        "meta": {
          "updateAt": 1747775286560,
          "createAt": 1747775279950
        }
      },
      "dVyyRAQs6Q0a4FAlAL2NV": {
        "id": "dVyyRAQs6Q0a4FAlAL2NV",
        "tableId": "8CR3LUh7Bu6E2K05mcn_1",
        "name": "",
        "comment": "",
        "dataType": "",
        "default": "",
        "options": 0,
        "ui": {
          "keys": 0,
          "widthName": 60,
          "widthComment": 60,
          "widthDataType": 60,
          "widthDefault": 60
        },
        "meta": {
          "updateAt": 1747775288198,
          "createAt": 1747775288198
        }
      },
      "y4KvWtTYP5JkQyTl04qSw": {
        "id": "y4KvWtTYP5JkQyTl04qSw",
        "tableId": "8CR3LUh7Bu6E2K05mcn_1",
        "name": "Pro_Disponibilidad",
        "comment": "",
        "dataType": "VARCHAR(20)",
        "default": "",
        "options": 0,
        "ui": {
          "keys": 0,
          "widthName": 101,
          "widthComment": 60,
          "widthDataType": 75,
          "widthDefault": 60
        },
        "meta": {
          "updateAt": 1747775338351,
          "createAt": 1747775324558
        }
      },
      "9JgLy7mw9-__CTecA4awu": {
        "id": "9JgLy7mw9-__CTecA4awu",
        "tableId": "9LsWnXQ9aNAfzXo7eTbcx",
        "name": "Usu_ID",
        "comment": "",
        "dataType": "INT",
        "default": "",
        "options": 10,
        "ui": {
          "keys": 1,
          "widthName": 60,
          "widthComment": 60,
          "widthDataType": 60,
          "widthDefault": 60
        },
        "meta": {
          "updateAt": 1747775447779,
          "createAt": 1747775345238
        }
      },
      "628tXiY8Gy0Pch8Zdgi_O": {
        "id": "628tXiY8Gy0Pch8Zdgi_O",
        "tableId": "9LsWnXQ9aNAfzXo7eTbcx",
        "name": "Usu_NombreC",
        "comment": "",
        "dataType": "VARCHAR(200)",
        "default": "",
        "options": 0,
        "ui": {
          "keys": 0,
          "widthName": 78,
          "widthComment": 60,
          "widthDataType": 81,
          "widthDefault": 60
        },
        "meta": {
          "updateAt": 1747775544359,
          "createAt": 1747775382942
        }
      },
      "zu1IWPs5vTy84TVlxcTxi": {
        "id": "zu1IWPs5vTy84TVlxcTxi",
        "tableId": "9LsWnXQ9aNAfzXo7eTbcx",
        "name": "Usu_DNI",
        "comment": "",
        "dataType": "INT",
        "default": "",
        "options": 0,
        "ui": {
          "keys": 0,
          "widthName": 60,
          "widthComment": 60,
          "widthDataType": 60,
          "widthDefault": 60
        },
        "meta": {
          "updateAt": 1747775414816,
          "createAt": 1747775403902
        }
      },
      "PP2F4Jel-PojUbzOTFvVv": {
        "id": "PP2F4Jel-PojUbzOTFvVv",
        "tableId": "9LsWnXQ9aNAfzXo7eTbcx",
        "name": "Usu_Correo",
        "comment": "",
        "dataType": "VARCHAR(150)",
        "default": "",
        "options": 0,
        "ui": {
          "keys": 0,
          "widthName": 63,
          "widthComment": 60,
          "widthDataType": 81,
          "widthDefault": 60
        },
        "meta": {
          "updateAt": 1747775452141,
          "createAt": 1747775415798
        }
      },
      "M7f5Y8k7tINzo7vqPXCu3": {
        "id": "M7f5Y8k7tINzo7vqPXCu3",
        "tableId": "ine2bTIkvQcuM8JenCMxe",
        "name": "Ag_ID",
        "comment": "",
        "dataType": "INT",
        "default": "",
        "options": 10,
        "ui": {
          "keys": 1,
          "widthName": 60,
          "widthComment": 60,
          "widthDataType": 60,
          "widthDefault": 60
        },
        "meta": {
          "updateAt": 1747775580137,
          "createAt": 1747775490110
        }
      },
      "Nfi4QI4AwNQ7y9YgIszbv": {
        "id": "Nfi4QI4AwNQ7y9YgIszbv",
        "tableId": "ine2bTIkvQcuM8JenCMxe",
        "name": "Ag_NombreC",
        "comment": "",
        "dataType": "VARCHAR(200)",
        "default": "",
        "options": 0,
        "ui": {
          "keys": 0,
          "widthName": 73,
          "widthComment": 60,
          "widthDataType": 81,
          "widthDefault": 60
        },
        "meta": {
          "updateAt": 1747775556279,
          "createAt": 1747775502726
        }
      },
      "HfusV_diGDY1MxIpoYQSm": {
        "id": "HfusV_diGDY1MxIpoYQSm",
        "tableId": "ine2bTIkvQcuM8JenCMxe",
        "name": "Ag_Correo",
        "comment": "",
        "dataType": "VARCHAR(150)",
        "default": "",
        "options": 0,
        "ui": {
          "keys": 0,
          "widthName": 60,
          "widthComment": 60,
          "widthDataType": 81,
          "widthDefault": 60
        },
        "meta": {
          "updateAt": 1747775569319,
          "createAt": 1747775557190
        }
      },
      "BPb6M5f0eyH3Wyu6rSV-a": {
        "id": "BPb6M5f0eyH3Wyu6rSV-a",
        "tableId": "ine2bTIkvQcuM8JenCMxe",
        "name": "Ag_Telefono",
        "comment": "",
        "dataType": "INT",
        "default": "",
        "options": 0,
        "ui": {
          "keys": 0,
          "widthName": 67,
          "widthComment": 60,
          "widthDataType": 60,
          "widthDefault": 60
        },
        "meta": {
          "updateAt": 1747775577616,
          "createAt": 1747775570126
        }
      },
      "czo1ePlKeE86yqB8Tzy71": {
        "id": "czo1ePlKeE86yqB8Tzy71",
        "tableId": "UECpcafYs5jqD4Jo9NzYu",
        "name": "Vis_ID",
        "comment": "",
        "dataType": "INT",
        "default": "",
        "options": 10,
        "ui": {
          "keys": 1,
          "widthName": 60,
          "widthComment": 60,
          "widthDataType": 60,
          "widthDefault": 60
        },
        "meta": {
          "updateAt": 1747775650932,
          "createAt": 1747775627246
        }
      },
      "2bD53c6vrEt1dwBku7WAZ": {
        "id": "2bD53c6vrEt1dwBku7WAZ",
        "tableId": "UECpcafYs5jqD4Jo9NzYu",
        "name": "Vis_Fecha",
        "comment": "",
        "dataType": "DATETIME",
        "default": "",
        "options": 0,
        "ui": {
          "keys": 0,
          "widthName": 60,
          "widthComment": 60,
          "widthDataType": 60,
          "widthDefault": 60
        },
        "meta": {
          "updateAt": 1747775648719,
          "createAt": 1747775637518
        }
      },
      "KkvXjknKbX7B5X-cumGZe": {
        "id": "KkvXjknKbX7B5X-cumGZe",
        "tableId": "32DQc-8Kt8b4ICwfTxYbx",
        "name": "Pub_ID",
        "comment": "",
        "dataType": "INT",
        "default": "",
        "options": 10,
        "ui": {
          "keys": 1,
          "widthName": 60,
          "widthComment": 60,
          "widthDataType": 60,
          "widthDefault": 60
        },
        "meta": {
          "updateAt": 1747775731591,
          "createAt": 1747775664342
        }
      },
      "KN-dxpfvX73zgXOZWE6V9": {
        "id": "KN-dxpfvX73zgXOZWE6V9",
        "tableId": "32DQc-8Kt8b4ICwfTxYbx",
        "name": "Pub_FechaP",
        "comment": "",
        "dataType": "DATETIME",
        "default": "",
        "options": 0,
        "ui": {
          "keys": 0,
          "widthName": 65,
          "widthComment": 60,
          "widthDataType": 60,
          "widthDefault": 60
        },
        "meta": {
          "updateAt": 1747775709823,
          "createAt": 1747775674246
        }
      },
      "N1UeOGXk8l6qj4TPTJcUc": {
        "id": "N1UeOGXk8l6qj4TPTJcUc",
        "tableId": "32DQc-8Kt8b4ICwfTxYbx",
        "name": "Pub_Descripcion",
        "comment": "",
        "dataType": "VARCHAR(300)",
        "default": "",
        "options": 0,
        "ui": {
          "keys": 0,
          "widthName": 89,
          "widthComment": 60,
          "widthDataType": 81,
          "widthDefault": 60
        },
        "meta": {
          "updateAt": 1747775728183,
          "createAt": 1747775711630
        }
      },
      "NsmDn9TD7cfFwHLIe16JI": {
        "id": "NsmDn9TD7cfFwHLIe16JI",
        "tableId": "L35OiQd2nzeUB99PqCeDp",
        "name": "Res_ID",
        "comment": "",
        "dataType": "INT",
        "default": "",
        "options": 10,
        "ui": {
          "keys": 1,
          "widthName": 60,
          "widthComment": 60,
          "widthDataType": 60,
          "widthDefault": 60
        },
        "meta": {
          "updateAt": 1747775805170,
          "createAt": 1747775737998
        }
      },
      "XoJjeY9qQQKZ0syZfm1wU": {
        "id": "XoJjeY9qQQKZ0syZfm1wU",
        "tableId": "L35OiQd2nzeUB99PqCeDp",
        "name": "Res_Descripcion",
        "comment": "",
        "dataType": "VARCHAR(300)",
        "default": "",
        "options": 0,
        "ui": {
          "keys": 0,
          "widthName": 87,
          "widthComment": 60,
          "widthDataType": 81,
          "widthDefault": 60
        },
        "meta": {
          "updateAt": 1747775778369,
          "createAt": 1747775749430
        }
      },
      "8q_OzybaLdy6_kLSnC8o1": {
        "id": "8q_OzybaLdy6_kLSnC8o1",
        "tableId": "L35OiQd2nzeUB99PqCeDp",
        "name": "Res_Califica",
        "comment": "",
        "dataType": "INT",
        "default": "",
        "options": 0,
        "ui": {
          "keys": 0,
          "widthName": 63,
          "widthComment": 60,
          "widthDataType": 60,
          "widthDefault": 60
        },
        "meta": {
          "updateAt": 1747775790112,
          "createAt": 1747775779374
        }
      },
      "28KfmFCUUOnQreRSS5q13": {
        "id": "28KfmFCUUOnQreRSS5q13",
        "tableId": "L35OiQd2nzeUB99PqCeDp",
        "name": "Res_Fecha",
        "comment": "",
        "dataType": "DATETIME",
        "default": "",
        "options": 0,
        "ui": {
          "keys": 0,
          "widthName": 60,
          "widthComment": 60,
          "widthDataType": 60,
          "widthDefault": 60
        },
        "meta": {
          "updateAt": 1747775801767,
          "createAt": 1747775790870
        }
      },
      "id2kmU8xcDxJf0mA_2GvE": {
        "id": "id2kmU8xcDxJf0mA_2GvE",
        "tableId": "JgOK8KJIWMkp047nzUywE",
        "name": "TiP_Tipo",
        "comment": "",
        "dataType": "VARCHAR(50)",
        "default": "",
        "options": 10,
        "ui": {
          "keys": 1,
          "widthName": 60,
          "widthComment": 60,
          "widthDataType": 75,
          "widthDefault": 60
        },
        "meta": {
          "updateAt": 1747775868274,
          "createAt": 1747775841830
        }
      },
      "It5YSy18HWegbYOBEmL1z": {
        "id": "It5YSy18HWegbYOBEmL1z",
        "tableId": "JgOK8KJIWMkp047nzUywE",
        "name": "",
        "comment": "",
        "dataType": "",
        "default": "",
        "options": 0,
        "ui": {
          "keys": 0,
          "widthName": 60,
          "widthComment": 60,
          "widthDataType": 60,
          "widthDefault": 60
        },
        "meta": {
          "updateAt": 1747775862911,
          "createAt": 1747775855510
        }
      },
      "iUiWEBF83HQ6QUBJlB3B5": {
        "id": "iUiWEBF83HQ6QUBJlB3B5",
        "tableId": "x7s47iTk7VF24-TR7pl-1",
        "name": "Dep_ID",
        "comment": "",
        "dataType": "INT",
        "default": "",
        "options": 10,
        "ui": {
          "keys": 1,
          "widthName": 60,
          "widthComment": 60,
          "widthDataType": 60,
          "widthDefault": 60
        },
        "meta": {
          "updateAt": 1747775930020,
          "createAt": 1747775877662
        }
      },
      "ykRa7iy7oS7-M-jXUo-kG": {
        "id": "ykRa7iy7oS7-M-jXUo-kG",
        "tableId": "x7s47iTk7VF24-TR7pl-1",
        "name": "",
        "comment": "",
        "dataType": "",
        "default": "",
        "options": 0,
        "ui": {
          "keys": 0,
          "widthName": 60,
          "widthComment": 60,
          "widthDataType": 60,
          "widthDefault": 60
        },
        "meta": {
          "updateAt": 1747775889191,
          "createAt": 1747775885374
        }
      },
      "YGP1EAkKeux6T-uwjyV3U": {
        "id": "YGP1EAkKeux6T-uwjyV3U",
        "tableId": "Q9zTRpze3Ct-XInVhqy2O",
        "name": "Pvc_ID",
        "comment": "",
        "dataType": "INT",
        "default": "",
        "options": 10,
        "ui": {
          "keys": 1,
          "widthName": 60,
          "widthComment": 60,
          "widthDataType": 60,
          "widthDefault": 60
        },
        "meta": {
          "updateAt": 1747775930920,
          "createAt": 1747775915726
        }
      },
      "r0iv5VwOH2UhFZf8HOCsa": {
        "id": "r0iv5VwOH2UhFZf8HOCsa",
        "tableId": "x7s47iTk7VF24-TR7pl-1",
        "name": "Dep_Desc",
        "comment": "",
        "dataType": "VARCHAR(150)",
        "default": "",
        "options": 0,
        "ui": {
          "keys": 0,
          "widthName": 60,
          "widthComment": 60,
          "widthDataType": 81,
          "widthDefault": 60
        },
        "meta": {
          "updateAt": 1747775944375,
          "createAt": 1747775931720
        }
      },
      "6VuQk97r0e_DpJLECfxtK": {
        "id": "6VuQk97r0e_DpJLECfxtK",
        "tableId": "Q9zTRpze3Ct-XInVhqy2O",
        "name": "Pvc_Desc",
        "comment": "",
        "dataType": "VARCHAR(150)",
        "default": "",
        "options": 0,
        "ui": {
          "keys": 0,
          "widthName": 60,
          "widthComment": 60,
          "widthDataType": 81,
          "widthDefault": 60
        },
        "meta": {
          "updateAt": 1747775955297,
          "createAt": 1747775948945
        }
      },
      "WmXGnVwLfffiRCMVKZPXj": {
        "id": "WmXGnVwLfffiRCMVKZPXj",
        "tableId": "Zy6H_d4fEmMmQ6c1w9ngv",
        "name": "Dtr_ID",
        "comment": "",
        "dataType": "INT",
        "default": "",
        "options": 10,
        "ui": {
          "keys": 1,
          "widthName": 60,
          "widthComment": 60,
          "widthDataType": 60,
          "widthDefault": 60
        },
        "meta": {
          "updateAt": 1747775983376,
          "createAt": 1747775962742
        }
      },
      "ijGqev_55c-Slqc2VgOU5": {
        "id": "ijGqev_55c-Slqc2VgOU5",
        "tableId": "Zy6H_d4fEmMmQ6c1w9ngv",
        "name": "Dtr_Desc",
        "comment": "",
        "dataType": "VARCHAR(150)",
        "default": "",
        "options": 0,
        "ui": {
          "keys": 0,
          "widthName": 60,
          "widthComment": 60,
          "widthDataType": 81,
          "widthDefault": 60
        },
        "meta": {
          "updateAt": 1747775981065,
          "createAt": 1747775976310
        }
      },
      "j9PckDovgAyDVEmSAakl2": {
        "id": "j9PckDovgAyDVEmSAakl2",
        "tableId": "QianxabkC7plIXeknbQ24",
        "name": "Due_ID",
        "comment": "",
        "dataType": "INT",
        "default": "",
        "options": 10,
        "ui": {
          "keys": 1,
          "widthName": 60,
          "widthComment": 60,
          "widthDataType": 60,
          "widthDefault": 60
        },
        "meta": {
          "updateAt": 1747776099528,
          "createAt": 1747776072710
        }
      },
      "vJUaprAztIhsfzTsE9btg": {
        "id": "vJUaprAztIhsfzTsE9btg",
        "tableId": "QianxabkC7plIXeknbQ24",
        "name": "Due_DNI",
        "comment": "",
        "dataType": "INT",
        "default": "",
        "options": 0,
        "ui": {
          "keys": 0,
          "widthName": 60,
          "widthComment": 60,
          "widthDataType": 60,
          "widthDefault": 60
        },
        "meta": {
          "updateAt": 1747776088760,
          "createAt": 1747776078262
        }
      },
      "IFXdeVPBeTeSpO0tPY0DE": {
        "id": "IFXdeVPBeTeSpO0tPY0DE",
        "tableId": "QianxabkC7plIXeknbQ24",
        "name": "Due_Correo",
        "comment": "",
        "dataType": "VARCHAR(150)",
        "default": "",
        "options": 0,
        "ui": {
          "keys": 0,
          "widthName": 65,
          "widthComment": 60,
          "widthDataType": 81,
          "widthDefault": 60
        },
        "meta": {
          "updateAt": 1747776094969,
          "createAt": 1747776089494
        }
      },
      "0B-3n9R4F2AA5RHBGFngv": {
        "id": "0B-3n9R4F2AA5RHBGFngv",
        "tableId": "JNxQVbXcTdRCSPeXcfoII",
        "name": "Cont_ID",
        "comment": "",
        "dataType": "INT",
        "default": "",
        "options": 0,
        "ui": {
          "keys": 0,
          "widthName": 60,
          "widthComment": 60,
          "widthDataType": 60,
          "widthDefault": 60
        },
        "meta": {
          "updateAt": 1747776134520,
          "createAt": 1747776113262
        }
      },
      "bviFpjIfyRJ19NX6FteTd": {
        "id": "bviFpjIfyRJ19NX6FteTd",
        "tableId": "JNxQVbXcTdRCSPeXcfoII",
        "name": "Cont_Fecha",
        "comment": "",
        "dataType": "DATETIME",
        "default": "",
        "options": 0,
        "ui": {
          "keys": 0,
          "widthName": 63,
          "widthComment": 60,
          "widthDataType": 60,
          "widthDefault": 60
        },
        "meta": {
          "updateAt": 1747776144015,
          "createAt": 1747776135198
        }
      },
      "o0SFDeJHKdVro0EII5SNG": {
        "id": "o0SFDeJHKdVro0EII5SNG",
        "tableId": "JNxQVbXcTdRCSPeXcfoII",
        "name": "",
        "comment": "",
        "dataType": "",
        "default": "",
        "options": 0,
        "ui": {
          "keys": 0,
          "widthName": 60,
          "widthComment": 60,
          "widthDataType": 60,
          "widthDefault": 60
        },
        "meta": {
          "updateAt": 1747776147927,
          "createAt": 1747776145118
        }
      },
      "IM9P-Ll101qZkiYwAPbwe": {
        "id": "IM9P-Ll101qZkiYwAPbwe",
        "tableId": "Q9zTRpze3Ct-XInVhqy2O",
        "name": "Dep_ID",
        "comment": "",
        "dataType": "INT",
        "default": "",
        "options": 8,
        "ui": {
          "keys": 2,
          "widthName": 60,
          "widthComment": 60,
          "widthDataType": 60,
          "widthDefault": 60
        },
        "meta": {
          "updateAt": 1747776166855,
          "createAt": 1747776166855
        }
      },
      "ylmsizYo2iEEPl9KC35Rt": {
        "id": "ylmsizYo2iEEPl9KC35Rt",
        "tableId": "Zy6H_d4fEmMmQ6c1w9ngv",
        "name": "Pvc_ID",
        "comment": "",
        "dataType": "INT",
        "default": "",
        "options": 8,
        "ui": {
          "keys": 2,
          "widthName": 60,
          "widthComment": 60,
          "widthDataType": 60,
          "widthDefault": 60
        },
        "meta": {
          "updateAt": 1747776170195,
          "createAt": 1747776170195
        }
      },
      "5tul_fHFqnHCw3_UGWzli": {
        "id": "5tul_fHFqnHCw3_UGWzli",
        "tableId": "8CR3LUh7Bu6E2K05mcn_1",
        "name": "Dtr_ID",
        "comment": "",
        "dataType": "INT",
        "default": "",
        "options": 8,
        "ui": {
          "keys": 2,
          "widthName": 60,
          "widthComment": 60,
          "widthDataType": 60,
          "widthDefault": 60
        },
        "meta": {
          "updateAt": 1747776236254,
          "createAt": 1747776236254
        }
      },
      "vGHJTPArO0DhAbOZ0Kt-e": {
        "id": "vGHJTPArO0DhAbOZ0Kt-e",
        "tableId": "8CR3LUh7Bu6E2K05mcn_1",
        "name": "Due_ID",
        "comment": "",
        "dataType": "INT",
        "default": "",
        "options": 8,
        "ui": {
          "keys": 2,
          "widthName": 60,
          "widthComment": 60,
          "widthDataType": 60,
          "widthDefault": 60
        },
        "meta": {
          "updateAt": 1747776245830,
          "createAt": 1747776245830
        }
      },
      "s56b71V8S6iJwFJ9vUDcB": {
        "id": "s56b71V8S6iJwFJ9vUDcB",
        "tableId": "8CR3LUh7Bu6E2K05mcn_1",
        "name": "TiP_Tipo",
        "comment": "",
        "dataType": "VARCHAR(50)",
        "default": "",
        "options": 8,
        "ui": {
          "keys": 2,
          "widthName": 60,
          "widthComment": 60,
          "widthDataType": 75,
          "widthDefault": 60
        },
        "meta": {
          "updateAt": 1747776250416,
          "createAt": 1747776250415
        }
      },
      "5MghgRmLD_5JS5nHmvv1i": {
        "id": "5MghgRmLD_5JS5nHmvv1i",
        "tableId": "UECpcafYs5jqD4Jo9NzYu",
        "name": "Usu_ID",
        "comment": "",
        "dataType": "INT",
        "default": "",
        "options": 8,
        "ui": {
          "keys": 2,
          "widthName": 60,
          "widthComment": 60,
          "widthDataType": 60,
          "widthDefault": 60
        },
        "meta": {
          "updateAt": 1747776319489,
          "createAt": 1747776319489
        }
      },
      "GAHtiB3XTmiALQLEjwvos": {
        "id": "GAHtiB3XTmiALQLEjwvos",
        "tableId": "UECpcafYs5jqD4Jo9NzYu",
        "name": "Pro_ID",
        "comment": "",
        "dataType": "INT",
        "default": "",
        "options": 8,
        "ui": {
          "keys": 2,
          "widthName": 60,
          "widthComment": 60,
          "widthDataType": 60,
          "widthDefault": 60
        },
        "meta": {
          "updateAt": 1747776323672,
          "createAt": 1747776323672
        }
      },
      "El8rdhaQJQ4UdBo3jz64n": {
        "id": "El8rdhaQJQ4UdBo3jz64n",
        "tableId": "UECpcafYs5jqD4Jo9NzYu",
        "name": "Ag_ID",
        "comment": "",
        "dataType": "INT",
        "default": "",
        "options": 8,
        "ui": {
          "keys": 2,
          "widthName": 60,
          "widthComment": 60,
          "widthDataType": 60,
          "widthDefault": 60
        },
        "meta": {
          "updateAt": 1747776343078,
          "createAt": 1747776343078
        }
      },
      "JWNYoVwL--kCG0n-9ef69": {
        "id": "JWNYoVwL--kCG0n-9ef69",
        "tableId": "32DQc-8Kt8b4ICwfTxYbx",
        "name": "Pro_ID",
        "comment": "",
        "dataType": "INT",
        "default": "",
        "options": 8,
        "ui": {
          "keys": 2,
          "widthName": 60,
          "widthComment": 60,
          "widthDataType": 60,
          "widthDefault": 60
        },
        "meta": {
          "updateAt": 1747776370903,
          "createAt": 1747776370903
        }
      },
      "Jrho93-J0SnjsFwhkIzU6": {
        "id": "Jrho93-J0SnjsFwhkIzU6",
        "tableId": "32DQc-8Kt8b4ICwfTxYbx",
        "name": "Usu_ID",
        "comment": "",
        "dataType": "INT",
        "default": "",
        "options": 8,
        "ui": {
          "keys": 0,
          "widthName": 60,
          "widthComment": 60,
          "widthDataType": 60,
          "widthDefault": 60
        },
        "meta": {
          "updateAt": 1747776374889,
          "createAt": 1747776374889
        }
      },
      "ogWk7gsXrqxZlt13_hiUW": {
        "id": "ogWk7gsXrqxZlt13_hiUW",
        "tableId": "L35OiQd2nzeUB99PqCeDp",
        "name": "Usu_ID",
        "comment": "",
        "dataType": "INT",
        "default": "",
        "options": 8,
        "ui": {
          "keys": 2,
          "widthName": 60,
          "widthComment": 60,
          "widthDataType": 60,
          "widthDefault": 60
        },
        "meta": {
          "updateAt": 1747776416944,
          "createAt": 1747776416944
        }
      },
      "5AFDkGa4rrE2vXhHsyFp9": {
        "id": "5AFDkGa4rrE2vXhHsyFp9",
        "tableId": "L35OiQd2nzeUB99PqCeDp",
        "name": "Pro_ID",
        "comment": "",
        "dataType": "INT",
        "default": "",
        "options": 8,
        "ui": {
          "keys": 2,
          "widthName": 60,
          "widthComment": 60,
          "widthDataType": 60,
          "widthDefault": 60
        },
        "meta": {
          "updateAt": 1747776443633,
          "createAt": 1747776443633
        }
      },
      "7nlM6yAoojrzXVtiI-G9s": {
        "id": "7nlM6yAoojrzXVtiI-G9s",
        "tableId": "JNxQVbXcTdRCSPeXcfoII",
        "name": "Usu_ID",
        "comment": "",
        "dataType": "INT",
        "default": "",
        "options": 8,
        "ui": {
          "keys": 2,
          "widthName": 60,
          "widthComment": 60,
          "widthDataType": 60,
          "widthDefault": 60
        },
        "meta": {
          "updateAt": 1747776465221,
          "createAt": 1747776465221
        }
      },
      "ngEuDxk8kKKj1NfZ_gwt3": {
        "id": "ngEuDxk8kKKj1NfZ_gwt3",
        "tableId": "YtVYbPYV1bAvrPaLvH0Vr",
        "name": "TiCon_ID",
        "comment": "",
        "dataType": "INT",
        "default": "",
        "options": 10,
        "ui": {
          "keys": 1,
          "widthName": 60,
          "widthComment": 60,
          "widthDataType": 60,
          "widthDefault": 60
        },
        "meta": {
          "updateAt": 1747776524220,
          "createAt": 1747776479792
        }
      },
      "oQ25oBTmxPwoNt9C-Rvs2": {
        "id": "oQ25oBTmxPwoNt9C-Rvs2",
        "tableId": "YtVYbPYV1bAvrPaLvH0Vr",
        "name": "TiCon_Tipo",
        "comment": "",
        "dataType": "VARCHAR(100)",
        "default": "",
        "options": 0,
        "ui": {
          "keys": 0,
          "widthName": 61,
          "widthComment": 60,
          "widthDataType": 81,
          "widthDefault": 60
        },
        "meta": {
          "updateAt": 1747776519671,
          "createAt": 1747776506046
        }
      },
      "LKHGJl0iWdmcoRnrEV8_5": {
        "id": "LKHGJl0iWdmcoRnrEV8_5",
        "tableId": "JNxQVbXcTdRCSPeXcfoII",
        "name": "TiCon_ID",
        "comment": "",
        "dataType": "INT",
        "default": "",
        "options": 8,
        "ui": {
          "keys": 2,
          "widthName": 60,
          "widthComment": 60,
          "widthDataType": 60,
          "widthDefault": 60
        },
        "meta": {
          "updateAt": 1747776532159,
          "createAt": 1747776532159
        }
      },
      "h-wTro9ZagsloOzMvZAZX": {
        "id": "h-wTro9ZagsloOzMvZAZX",
        "tableId": "JNxQVbXcTdRCSPeXcfoII",
        "name": "Ag_ID",
        "comment": "",
        "dataType": "INT",
        "default": "",
        "options": 8,
        "ui": {
          "keys": 2,
          "widthName": 60,
          "widthComment": 60,
          "widthDataType": 60,
          "widthDefault": 60
        },
        "meta": {
          "updateAt": 1747776540129,
          "createAt": 1747776540128
        }
      },
      "jxQXJJFp-W5WJj99fyImZ": {
        "id": "jxQXJJFp-W5WJj99fyImZ",
        "tableId": "JNxQVbXcTdRCSPeXcfoII",
        "name": "Pro_ID",
        "comment": "",
        "dataType": "INT",
        "default": "",
        "options": 8,
        "ui": {
          "keys": 2,
          "widthName": 60,
          "widthComment": 60,
          "widthDataType": 60,
          "widthDefault": 60
        },
        "meta": {
          "updateAt": 1747776624211,
          "createAt": 1747776624211
        }
      },
      "vdJJcyNVV6gHN4o2dcmKj": {
        "id": "vdJJcyNVV6gHN4o2dcmKj",
        "tableId": "5dHesMonnOs6bORmG-b_M",
        "name": "Pa_ID",
        "comment": "",
        "dataType": "INT",
        "default": "",
        "options": 10,
        "ui": {
          "keys": 1,
          "widthName": 60,
          "widthComment": 60,
          "widthDataType": 60,
          "widthDefault": 60
        },
        "meta": {
          "updateAt": 1747776774097,
          "createAt": 1747776728846
        }
      },
      "ayxZ1XrhAbvKEK2Hs1NTJ": {
        "id": "ayxZ1XrhAbvKEK2Hs1NTJ",
        "tableId": "5dHesMonnOs6bORmG-b_M",
        "name": "Pa_Fecha",
        "comment": "",
        "dataType": "DATETIME",
        "default": "",
        "options": 0,
        "ui": {
          "keys": 0,
          "widthName": 60,
          "widthComment": 60,
          "widthDataType": 60,
          "widthDefault": 60
        },
        "meta": {
          "updateAt": 1747776755536,
          "createAt": 1747776733454
        }
      },
      "2_XtzvJfTMEVkpdA1ZHeG": {
        "id": "2_XtzvJfTMEVkpdA1ZHeG",
        "tableId": "5dHesMonnOs6bORmG-b_M",
        "name": "Pa_Monto",
        "comment": "",
        "dataType": "MONEY",
        "default": "",
        "options": 0,
        "ui": {
          "keys": 0,
          "widthName": 60,
          "widthComment": 60,
          "widthDataType": 60,
          "widthDefault": 60
        },
        "meta": {
          "updateAt": 1747776757480,
          "createAt": 1747776739174
        }
      },
      "3yiBDSu0Fs8ZJjyQMLwzJ": {
        "id": "3yiBDSu0Fs8ZJjyQMLwzJ",
        "tableId": "5dHesMonnOs6bORmG-b_M",
        "name": "Pa_Tipo",
        "comment": "",
        "dataType": "VARCHAR(50)",
        "default": "",
        "options": 0,
        "ui": {
          "keys": 0,
          "widthName": 60,
          "widthComment": 60,
          "widthDataType": 75,
          "widthDefault": 60
        },
        "meta": {
          "updateAt": 1747776771559,
          "createAt": 1747776743766
        }
      },
      "RdkkDnmVr8n8N8hQf2cZr": {
        "id": "RdkkDnmVr8n8N8hQf2cZr",
        "tableId": "JNxQVbXcTdRCSPeXcfoII",
        "name": "Pa_ID",
        "comment": "",
        "dataType": "INT",
        "default": "",
        "options": 8,
        "ui": {
          "keys": 2,
          "widthName": 60,
          "widthComment": 60,
          "widthDataType": 60,
          "widthDefault": 60
        },
        "meta": {
          "updateAt": 1747776779781,
          "createAt": 1747776779781
        }
      },
      "VCO6qcs9jiBSCD7YtOWFx": {
        "id": "VCO6qcs9jiBSCD7YtOWFx",
        "tableId": "32DQc-8Kt8b4ICwfTxYbx",
        "name": "Due_ID",
        "comment": "",
        "dataType": "INT",
        "default": "",
        "options": 8,
        "ui": {
          "keys": 2,
          "widthName": 60,
          "widthComment": 60,
          "widthDataType": 60,
          "widthDefault": 60
        },
        "meta": {
          "updateAt": 1747777108641,
          "createAt": 1747777108641
        }
      }
    },
    "relationshipEntities": {
      "m0Az5BGIEZoUg45vhnAJC": {
        "id": "m0Az5BGIEZoUg45vhnAJC",
        "identification": false,
        "relationshipType": 8,
        "startRelationshipType": 2,
        "start": {
          "tableId": "x7s47iTk7VF24-TR7pl-1",
          "columnIds": [
            "iUiWEBF83HQ6QUBJlB3B5"
          ],
          "x": 229.2057,
          "y": 717.2167,
          "direction": 4
        },
        "end": {
          "tableId": "Q9zTRpze3Ct-XInVhqy2O",
          "columnIds": [
            "IM9P-Ll101qZkiYwAPbwe"
          ],
          "x": 229.0032,
          "y": 622.3963,
          "direction": 8
        },
        "meta": {
          "updateAt": 1747776166855,
          "createAt": 1747776166855
        }
      },
      "YsMnr6maLTkx3jvDCpCCL": {
        "id": "YsMnr6maLTkx3jvDCpCCL",
        "identification": false,
        "relationshipType": 8,
        "startRelationshipType": 2,
        "start": {
          "tableId": "Q9zTRpze3Ct-XInVhqy2O",
          "columnIds": [
            "YGP1EAkKeux6T-uwjyV3U"
          ],
          "x": 229.0032,
          "y": 494.3963,
          "direction": 4
        },
        "end": {
          "tableId": "Zy6H_d4fEmMmQ6c1w9ngv",
          "columnIds": [
            "ylmsizYo2iEEPl9KC35Rt"
          ],
          "x": 229.0345,
          "y": 408.028,
          "direction": 8
        },
        "meta": {
          "updateAt": 1747776170195,
          "createAt": 1747776170195
        }
      },
      "D5oWdKVx7ak4WFyKNfLB_": {
        "id": "D5oWdKVx7ak4WFyKNfLB_",
        "identification": false,
        "relationshipType": 8,
        "startRelationshipType": 2,
        "start": {
          "tableId": "Zy6H_d4fEmMmQ6c1w9ngv",
          "columnIds": [
            "WmXGnVwLfffiRCMVKZPXj"
          ],
          "x": 422.0345,
          "y": 344.028,
          "direction": 2
        },
        "end": {
          "tableId": "8CR3LUh7Bu6E2K05mcn_1",
          "columnIds": [
            "5tul_fHFqnHCw3_UGWzli"
          ],
          "x": 738.6185,
          "y": 483.7591666666667,
          "direction": 1
        },
        "meta": {
          "updateAt": 1747776236254,
          "createAt": 1747776236254
        }
      },
      "8uwB5RWuMGtoeEtpHmbtT": {
        "id": "8uwB5RWuMGtoeEtpHmbtT",
        "identification": false,
        "relationshipType": 16,
        "startRelationshipType": 2,
        "start": {
          "tableId": "QianxabkC7plIXeknbQ24",
          "columnIds": [
            "j9PckDovgAyDVEmSAakl2"
          ],
          "x": 414.1627,
          "y": 208.90460000000002,
          "direction": 2
        },
        "end": {
          "tableId": "8CR3LUh7Bu6E2K05mcn_1",
          "columnIds": [
            "vGHJTPArO0DhAbOZ0Kt-e"
          ],
          "x": 738.6185,
          "y": 409.09250000000003,
          "direction": 1
        },
        "meta": {
          "updateAt": 1747776245830,
          "createAt": 1747776245830
        }
      },
      "AWMGbkcnmF_XmtedoHUfM": {
        "id": "AWMGbkcnmF_XmtedoHUfM",
        "identification": false,
        "relationshipType": 8,
        "startRelationshipType": 2,
        "start": {
          "tableId": "JgOK8KJIWMkp047nzUywE",
          "columnIds": [
            "id2kmU8xcDxJf0mA_2GvE"
          ],
          "x": 625.8725,
          "y": 61.8244,
          "direction": 2
        },
        "end": {
          "tableId": "8CR3LUh7Bu6E2K05mcn_1",
          "columnIds": [
            "s56b71V8S6iJwFJ9vUDcB"
          ],
          "x": 738.6185,
          "y": 334.42583333333334,
          "direction": 1
        },
        "meta": {
          "updateAt": 1747776250416,
          "createAt": 1747776250416
        }
      },
      "uWiHvYVIhZXExPL7_wz6L": {
        "id": "uWiHvYVIhZXExPL7_wz6L",
        "identification": false,
        "relationshipType": 16,
        "startRelationshipType": 2,
        "start": {
          "tableId": "9LsWnXQ9aNAfzXo7eTbcx",
          "columnIds": [
            "9JgLy7mw9-__CTecA4awu"
          ],
          "x": 1581.584,
          "y": 341.2553,
          "direction": 1
        },
        "end": {
          "tableId": "UECpcafYs5jqD4Jo9NzYu",
          "columnIds": [
            "5MghgRmLD_5JS5nHmvv1i"
          ],
          "x": 1682.9167,
          "y": 213.2822,
          "direction": 8
        },
        "meta": {
          "updateAt": 1747776319489,
          "createAt": 1747776319489
        }
      },
      "FZ1_VBBbh8kT4Yg8kCVVd": {
        "id": "FZ1_VBBbh8kT4Yg8kCVVd",
        "identification": false,
        "relationshipType": 16,
        "startRelationshipType": 2,
        "start": {
          "tableId": "8CR3LUh7Bu6E2K05mcn_1",
          "columnIds": [
            "a5elWrybvmcG4iFuMdC3_"
          ],
          "x": 1165.6185,
          "y": 353.0925,
          "direction": 2
        },
        "end": {
          "tableId": "UECpcafYs5jqD4Jo9NzYu",
          "columnIds": [
            "GAHtiB3XTmiALQLEjwvos"
          ],
          "x": 1409.1667,
          "y": 125.2822,
          "direction": 1
        },
        "meta": {
          "updateAt": 1747776323672,
          "createAt": 1747776323672
        }
      },
      "7_zab4jHHCB_G3M7h7s_n": {
        "id": "7_zab4jHHCB_G3M7h7s_n",
        "identification": false,
        "relationshipType": 16,
        "startRelationshipType": 2,
        "start": {
          "tableId": "ine2bTIkvQcuM8JenCMxe",
          "columnIds": [
            "M7f5Y8k7tINzo7vqPXCu3"
          ],
          "x": 1501.3858,
          "y": 915.797,
          "direction": 4
        },
        "end": {
          "tableId": "UECpcafYs5jqD4Jo9NzYu",
          "columnIds": [
            "El8rdhaQJQ4UdBo3jz64n"
          ],
          "x": 1500.4167,
          "y": 213.2822,
          "direction": 8
        },
        "meta": {
          "updateAt": 1747776343078,
          "createAt": 1747776343078
        }
      },
      "Jazl1WYFgzFc92m5Woi53": {
        "id": "Jazl1WYFgzFc92m5Woi53",
        "identification": false,
        "relationshipType": 16,
        "startRelationshipType": 2,
        "start": {
          "tableId": "8CR3LUh7Bu6E2K05mcn_1",
          "columnIds": [
            "a5elWrybvmcG4iFuMdC3_"
          ],
          "x": 952.1185,
          "y": 297.0925,
          "direction": 4
        },
        "end": {
          "tableId": "32DQc-8Kt8b4ICwfTxYbx",
          "columnIds": [
            "JWNYoVwL--kCG0n-9ef69"
          ],
          "x": 950.1705,
          "y": 205.0654,
          "direction": 8
        },
        "meta": {
          "updateAt": 1747776370903,
          "createAt": 1747776370903
        }
      },
      "Fgvp8Ln0o3RL5Oa7yrd8x": {
        "id": "Fgvp8Ln0o3RL5Oa7yrd8x",
        "identification": false,
        "relationshipType": 16,
        "startRelationshipType": 2,
        "start": {
          "tableId": "9LsWnXQ9aNAfzXo7eTbcx",
          "columnIds": [
            "9JgLy7mw9-__CTecA4awu"
          ],
          "x": 1783.584,
          "y": 455.2553,
          "direction": 8
        },
        "end": {
          "tableId": "L35OiQd2nzeUB99PqCeDp",
          "columnIds": [
            "ogWk7gsXrqxZlt13_hiUW"
          ],
          "x": 1780.298,
          "y": 615.0032,
          "direction": 4
        },
        "meta": {
          "updateAt": 1747776416944,
          "createAt": 1747776416944
        }
      },
      "xJgE60TVswrGbI4OJcFA8": {
        "id": "xJgE60TVswrGbI4OJcFA8",
        "identification": false,
        "relationshipType": 16,
        "startRelationshipType": 2,
        "start": {
          "tableId": "8CR3LUh7Bu6E2K05mcn_1",
          "columnIds": [
            "a5elWrybvmcG4iFuMdC3_"
          ],
          "x": 1165.6185,
          "y": 465.0925,
          "direction": 2
        },
        "end": {
          "tableId": "L35OiQd2nzeUB99PqCeDp",
          "columnIds": [
            "5AFDkGa4rrE2vXhHsyFp9"
          ],
          "x": 1573.798,
          "y": 715.0032,
          "direction": 1
        },
        "meta": {
          "updateAt": 1747776443633,
          "createAt": 1747776443633
        }
      },
      "C0xf5tBJob8rp-ZuqWMa4": {
        "id": "C0xf5tBJob8rp-ZuqWMa4",
        "identification": false,
        "relationshipType": 16,
        "startRelationshipType": 2,
        "start": {
          "tableId": "9LsWnXQ9aNAfzXo7eTbcx",
          "columnIds": [
            "9JgLy7mw9-__CTecA4awu"
          ],
          "x": 1581.584,
          "y": 417.2553,
          "direction": 1
        },
        "end": {
          "tableId": "JNxQVbXcTdRCSPeXcfoII",
          "columnIds": [
            "7nlM6yAoojrzXVtiI-G9s"
          ],
          "x": 1137.5317,
          "y": 687.6917,
          "direction": 2
        },
        "meta": {
          "updateAt": 1747776465221,
          "createAt": 1747776465221
        }
      },
      "XsI0of2u7hNW6SsRTSYdn": {
        "id": "XsI0of2u7hNW6SsRTSYdn",
        "identification": false,
        "relationshipType": 8,
        "startRelationshipType": 2,
        "start": {
          "tableId": "YtVYbPYV1bAvrPaLvH0Vr",
          "columnIds": [
            "ngEuDxk8kKKj1NfZ_gwt3"
          ],
          "x": 958.5506,
          "y": 966.1248,
          "direction": 4
        },
        "end": {
          "tableId": "JNxQVbXcTdRCSPeXcfoII",
          "columnIds": [
            "LKHGJl0iWdmcoRnrEV8_5"
          ],
          "x": 953.5317,
          "y": 855.6917,
          "direction": 8
        },
        "meta": {
          "updateAt": 1747776532159,
          "createAt": 1747776532159
        }
      },
      "MJE-sSUl4563d0zeG8nTi": {
        "id": "MJE-sSUl4563d0zeG8nTi",
        "identification": false,
        "relationshipType": 16,
        "startRelationshipType": 2,
        "start": {
          "tableId": "ine2bTIkvQcuM8JenCMxe",
          "columnIds": [
            "M7f5Y8k7tINzo7vqPXCu3"
          ],
          "x": 1301.8858,
          "y": 991.797,
          "direction": 1
        },
        "end": {
          "tableId": "JNxQVbXcTdRCSPeXcfoII",
          "columnIds": [
            "h-wTro9ZagsloOzMvZAZX"
          ],
          "x": 1137.5317,
          "y": 799.6917,
          "direction": 2
        },
        "meta": {
          "updateAt": 1747776540129,
          "createAt": 1747776540129
        }
      },
      "DLXefKcCVqoJxpxTMqjZ5": {
        "id": "DLXefKcCVqoJxpxTMqjZ5",
        "identification": false,
        "relationshipType": 8,
        "startRelationshipType": 2,
        "start": {
          "tableId": "8CR3LUh7Bu6E2K05mcn_1",
          "columnIds": [
            "a5elWrybvmcG4iFuMdC3_"
          ],
          "x": 952.1185,
          "y": 521.0925,
          "direction": 8
        },
        "end": {
          "tableId": "JNxQVbXcTdRCSPeXcfoII",
          "columnIds": [
            "jxQXJJFp-W5WJj99fyImZ"
          ],
          "x": 953.5317,
          "y": 631.6917,
          "direction": 4
        },
        "meta": {
          "updateAt": 1747776626654,
          "createAt": 1747776624211
        }
      },
      "mNP-5qpgEVbwRPn8R1NMs": {
        "id": "mNP-5qpgEVbwRPn8R1NMs",
        "identification": false,
        "relationshipType": 8,
        "startRelationshipType": 2,
        "start": {
          "tableId": "5dHesMonnOs6bORmG-b_M",
          "columnIds": [
            "vdJJcyNVV6gHN4o2dcmKj"
          ],
          "x": 618.4088,
          "y": 927.7051,
          "direction": 2
        },
        "end": {
          "tableId": "JNxQVbXcTdRCSPeXcfoII",
          "columnIds": [
            "RdkkDnmVr8n8N8hQf2cZr"
          ],
          "x": 769.5317,
          "y": 743.6917,
          "direction": 1
        },
        "meta": {
          "updateAt": 1747776779781,
          "createAt": 1747776779781
        }
      },
      "b5ru3fwcXNfo30Wvse_12": {
        "id": "b5ru3fwcXNfo30Wvse_12",
        "identification": false,
        "relationshipType": 16,
        "startRelationshipType": 2,
        "start": {
          "tableId": "QianxabkC7plIXeknbQ24",
          "columnIds": [
            "j9PckDovgAyDVEmSAakl2"
          ],
          "x": 414.1627,
          "y": 144.90460000000002,
          "direction": 2
        },
        "end": {
          "tableId": "32DQc-8Kt8b4ICwfTxYbx",
          "columnIds": [
            "VCO6qcs9jiBSCD7YtOWFx"
          ],
          "x": 742.6705,
          "y": 117.0654,
          "direction": 1
        },
        "meta": {
          "updateAt": 1747777108641,
          "createAt": 1747777108641
        }
      }
    },
    "indexEntities": {},
    "indexColumnEntities": {},
    "memoEntities": {}
  }
}